{
    "links": [
      {
        "href": "https://github.com/subasish",
        "icon": "FaGithub",
        "color": "white"
      },
      {
        "href": "https://www.linkedin.com/in/subasishdas/",
        "icon": "FaLinkedin",
        "color": "blue.300"
      },
      {
        "href": "https://scholar.google.com/citations?user=qK-YgxAAAAAJ&hl=en",
        "icon": "SiGooglescholar",
        "color": "white.700"
      },
      {
        "href": "https://twitter.com/subasish_das",
        "icon": "FaTwitter",
        "color": "blue.300"
      },
      {
        "href": "https://www.researchgate.net/profile/Subasish-Das",
        "icon": "FaResearchgate",
        "color": "white.600"
      }
    ]
  }
  