{
    "postdoctoralResearchAssociates": [
      {
        "name": "Md. Nasim Khan",
        "department": "",
        "institution": "TXST",
        "years": "2022-Pre",
        "linkedinProfile": "https://www.linkedin.com/in/nasim045/",
        "email": "rab347@txstate.edu",
        "profilePicture":"https://media.licdn.com/dms/image/v2/D5603AQExcXv3_EGaNw/profile-displayphoto-shrink_800_800/profile-displayphoto-shrink_800_800/0/1706279446862?e=1730937600&v=beta&t=_qGJqEF4M7FGjbmfQAVZ2mGLf9n4dotguUliLQTiHfI"
      },
      {
        "name": "Soheil Sohrabi",
        "department": "",
        "institution": "TTI",
        "years": "2021-2022",
        "linkedinProfile": "",
        "email": ""
      }
    ],
    "phdStudents": [
      {
        "name": "Jinli Liu",
        "department": "Geography",
        "institution": "TXST",
        "years": "2022-current",
        "linkedinProfile": "dipeshpandit12",
        "email": "rab347@txstate.edu"
      },
      {
        "name": "Amir Hossein Oliaee",
        "department": "Architecture",
        "institution": "TAMU",
        "years": "2022",
        "linkedinProfile": "https://www.linkedin.com/in/oliaee/",
        "email": "",
        "profilePicture": "https://media.licdn.com/dms/image/v2/D4D03AQFBZBakrdGG6Q/profile-displayphoto-shrink_800_800/profile-displayphoto-shrink_800_800/0/1704919888398?e=1730937600&v=beta&t=JyUvS1kRG4HqYMaPuw4m6UzCdD3daONVXh7i-i3BAcg"
      },
      {
        "name": "Nuzhat Kabir",
        "department": "Civil Engineering",
        "institution": "TAMU",
        "years": "2022",
        "linkedinProfile": "",
        "email": ""
      },
      {
        "name": "Musfira Rahman",
        "department": "Civil Engineering",
        "institution": "TAMU",
        "years": "2021",
        "linkedinProfile": "https://www.linkedin.com/in/musfira-rahman/",
        "email": "",
        "profilePicture":"https://media.licdn.com/dms/image/v2/D5603AQEDEZENgzU5SA/profile-displayphoto-shrink_800_800/profile-displayphoto-shrink_800_800/0/1703225636347?e=1730937600&v=beta&t=ydVB8-cUaKFP8MLcXey6gORhftN3CdTfeI4NIvkGt9c"
      },
      {
        "name": "Yanmo Wang",
        "department": "Civil Engineering",
        "institution": "TAMU",
        "years": "2021-2022",
        "linkedinProfile": "",
        "email": ""
      },
      {
        "name": "Zihang Wei",
        "department": "Civil Engineering",
        "institution": "TAMU",
        "years": "2020-2022",
        "linkedinProfile": "https://www.linkedin.com/in/zihang-wei-b41054103/",
        "email": "",
        "profilePicture":"https://media.licdn.com/dms/image/v2/D5603AQHlei3LrJf-CA/profile-displayphoto-shrink_800_800/profile-displayphoto-shrink_800_800/0/1705808864565?e=1730937600&v=beta&t=h2Dd0Z_72JDvoQzLrZwxwfZ-7dZzEJjS5fwop6CtHC4"
      },
      {
        "name": "Ali Khodadadi",
        "department": "Civil Engineering",
        "institution": "TAMU",
        "years": "2019-2021",
        "linkedinProfile": "",
        "email": ""
      },
      {
        "name": "Shruti Ashraf",
        "department": "Civil Engineering",
        "institution": "TAMU",
        "years": "2018-2019",
        "linkedinProfile": "https://www.linkedin.com/in/sruthiashraf/",
        "email": "",
        "profilePicture":"https://media.licdn.com/dms/image/v2/D5603AQHgSydJTVnjyQ/profile-displayphoto-shrink_800_800/profile-displayphoto-shrink_800_800/0/1686810336240?e=1730937600&v=beta&t=3-nkiCADCwC0-1rRxuKOQdvuPCc5oUs5C4QVojkwrVs"
      },
      {
        "name": "Chaolun Ma",
        "department": "Civil Engineering",
        "institution": "TAMU",
        "years": "2018-2019",
        "linkedinProfile": "https://www.linkedin.com/in/chaolun-ma-67732b77/",
        "email": "",
        "profilePicture":"https://media.licdn.com/dms/image/v2/C4E03AQGFeKs19zbqWw/profile-displayphoto-shrink_800_800/profile-displayphoto-shrink_800_800/0/1608781557691?e=1730937600&v=beta&t=Bsbjg7PhUlDnYtgGwV4LnOQIcMSVaQ9699mct2Iw2LE"
      },
      {
        "name": "Songjukta Datta",
        "department": "Civil Engineering",
        "institution": "TAMU",
        "years": "2017-2018",
        "linkedinProfile": "https://www.linkedin.com/in/songjukta/",
        "email": "",
        "profilePicture":"https://media.licdn.com/dms/image/v2/D5603AQFRG1W2uGkoXw/profile-displayphoto-shrink_800_800/profile-displayphoto-shrink_800_800/0/1722680716325?e=1730937600&v=beta&t=Lgzg2bbMDf2v3wVfwhRSR1ZsvQliIcrjWnb0feMNk1Q"
      }
    ],
    "msStudents": [
      {
        "name": "Vikram Agarwal",
        "department": "Civil Engineering",
        "institution": "TAMU",
        "years": "2020-2021",
        "linkedinProfile": "https://www.linkedin.com/in/agarwal-vikram/",
        "email": "",
        "profilePicture":"https://media.licdn.com/dms/image/v2/C4E03AQFcSl406wY4CA/profile-displayphoto-shrink_800_800/profile-displayphoto-shrink_800_800/0/1599059144846?e=1730937600&v=beta&t=lh0PPglBSqbIcOS2GPJkzd71msH7_D-zutAvdDXe9q8"
      },
      {
        "name": "Ruihong Wang",
        "department": "Electrical and CoE",
        "institution": "TAMU",
        "years": "2019-2020",
        "linkedinProfile": "https://www.linkedin.com/in/ruihong-wang-b5330a176/",
        "email": "",
        "profilePicture":"https://media.licdn.com/dms/image/v2/C4E03AQFSl4xUFaFyFQ/profile-displayphoto-shrink_800_800/profile-displayphoto-shrink_800_800/0/1565570288164?e=1730937600&v=beta&t=JreekPX7H-HUXf_yStYPTYmaAem-GUKc8RSSh1DTaTg"
      },
      {
        "name": "Nabila Nazneen",
        "department": "Chemical Engineering",
        "institution": "TAMU",
        "years": "2019-2020",
        "linkedinProfile": "",
        "email": ""
      },
      {
        "name": "Samia Tasnim",
        "department": "Public Health",
        "institution": "TAMU",
        "years": "2018-2019",
        "linkedinProfile": "https://www.linkedin.com/in/samiatasnim53/",
        "email": "",
        "profilePicture":"https://media.licdn.com/dms/image/v2/C5103AQHoW9qJX1nHCA/profile-displayphoto-shrink_800_800/profile-displayphoto-shrink_800_800/0/1581013567233?e=1730937600&v=beta&t=XOIA_l_FQZzfupJYSTSXB8Q9maZrGrlmvUciVcodjCM"
      },
      {
        "name": "Nusrat Trisha",
        "department": "Public Health",
        "institution": "TAMU",
        "years": "2019-2021",
        "linkedinProfile": "https://www.linkedin.com/in/nftrisha27/",
        "email": "",
        "profilePicture":"https://media.licdn.com/dms/image/v2/C4E03AQFOP44c1ssGBw/profile-displayphoto-shrink_800_800/profile-displayphoto-shrink_800_800/0/1649117017637?e=1730937600&v=beta&t=eqSuFb9y5RH26G51JDsPUIAYTw1bSg-m0xwZ5u8WUJc"
      },
      {
        "name": "Tahmida Shimu",
        "department": "Civil Engineering",
        "institution": "TAMU",
        "years": "2018-2019",
        "linkedinProfile": "https://www.linkedin.com/in/tahmida-shimu/",
        "email": "",
        "profilePicture":"https://media.licdn.com/dms/image/v2/D5603AQEWDs4GNGzURg/profile-displayphoto-shrink_800_800/profile-displayphoto-shrink_800_800/0/1671410883790?e=1730937600&v=beta&t=SxDfauQavF3lTdAxiu5Yva9gZPPWX1rYNqeIBIzSeKU"
      },
      {
        "name": "Bita Maraghehpour",
        "department": "Public Health",
        "institution": "TAMU",
        "years": "2017-2019",
        "linkedinProfile": "",
        "email": ""
      },
      {
        "name": "Apoorba Bibeka",
        "department": "Civil Engineering",
        "institution": "TAMU",
        "years": "2016-2019",
        "linkedinProfile": "",
        "email": "",
        "profilePicture":""
      },
      {
        "name": "Yucong Du",
        "department": "Civil Engineering",
        "institution": "TAMU",
        "years": "2016-2017",
        "linkedinProfile": "https://www.linkedin.com/in/yucong-du-pe-9a99a8144/",
        "email": "",
        "profilePicture":"https://media.licdn.com/dms/image/v2/D4E03AQH5pdhWxnKC0A/profile-displayphoto-shrink_800_800/profile-displayphoto-shrink_800_800/0/1706214178747?e=1730937600&v=beta&t=LQ3yRh8U_RdGw-lf1_fUs3-GDyw5JLTeV_IhNdJ4FZo"
      },
      {
        "name": "Sadia Najneen",
        "department": "Public Health",
        "institution": "TAMU",
        "years": "2018-2019",
        "linkedinProfile": "https://www.linkedin.com/in/sadia-najneen-9a5b10191/",
        "email": "",
        "profilePicture":"https://media.licdn.com/dms/image/v2/C5603AQEatehrQmtcsg/profile-displayphoto-shrink_800_800/profile-displayphoto-shrink_800_800/0/1611868738074?e=1730937600&v=beta&t=eg58jc5O_0Kt9PzG8I-ZdkmsrQauJbwA1Vp1ZyCg2zU"
      },
      {
        "name": "Isha Narsaria",
        "department": "Civil Engineering",
        "institution": "TAMU",
        "years": "2018-2019",
        "linkedinProfile": "https://www.linkedin.com/in/isha-narsaria/?originalSubdomain=in",
        "email": "",
        "profilePicture":"https://media.licdn.com/dms/image/v2/D4E03AQFPajZp98oeJg/profile-displayphoto-shrink_800_800/profile-displayphoto-shrink_800_800/0/1649047028699?e=1730937600&v=beta&t=8Eg3Z0cm83qhO6XZ7zdjNnsu-3fIcyWJrhys4Y8I58g"
      },
      {
        "name": "Noor-A Nazia",
        "department": "Computer Science",
        "institution": "TAMI",
        "years": "2018-2019",
        "linkedinProfile": "",
        "email": ""
      },
      {
        "name": "Condor Manaswini",
        "department": "Civil Engineering",
        "institution": "TAMU",
        "years": "2018-2019",
        "linkedinProfile": "",
        "email": ""
      },
      {
        "name": "Alence Poudel",
        "department": "Civil Engineering",
        "institution": "TAMU",
        "years": "2018-2019",
        "linkedinProfile": "",
        "email": ""
      },
      {
        "name": "Bharadwaj Bommanayakanahalli",
        "department": "Civil Engineering",
        "institution": "TAMU",
        "years": "2016-2017",
        "linkedinProfile": "",
        "email": ""
      },
      {
        "name": "Tamanna Tasnum",
        "department": "Construction Science",
        "institution": "TAMU",
        "years": "2016",
        "linkedinProfile": "",
        "email": ""
      }
    ],
    "undergraduateStudents": [
      {
        "name": "Juan Gonzalez",
        "department": "Civil Engineering",
        "institution": "TAMU",
        "years": "2022-2023",
        "linkedinProfile": "https://www.linkedin.com/in/juandiegocruzgonzalez/",
        "email": "",
        "profilePicture":"https://media.licdn.com/dms/image/v2/D5603AQG3SFDWOUp3yw/profile-displayphoto-shrink_800_800/profile-displayphoto-shrink_800_800/0/1668551595487?e=1730937600&v=beta&t=z0_gUxKHMpRHzE30uBLbIV9TpYvngjySS7f8hiIEqtk"
      },
      {
        "name": "Valerie Vierkant",
        "department": "Psychology",
        "institution": "TAMU",
        "years": "2019-2023",
        "linkedinProfile": "",
        "email": ""
      },
      {
        "name": "Jaxson Murray",
        "department": "Civil Engineering",
        "institution": "TAMU",
        "years": "2022",
        "linkedinProfile": "",
        "email": ""
      },
      {
        "name": "Ashley Trujillo",
        "department": "Civil Engineering",
        "institution": "TAMU",
        "years": "2021-2022",
        "linkedinProfile": "",
        "email": ""
      },
      {
        "name": "Vinesh Ravuri",
        "department": "Computer Science",
        "institution": "TAMU",
        "years": "2021",
        "linkedinProfile": "",
        "email": ""
      },
      {
        "name": "Magdalena Theel",
        "department": "Psychology",
        "institution": "TAMU",
        "years": "2017-2020",
        "linkedinProfile": "",
        "email": ""
      },
      {
        "name": "Turzo Bose",
        "department": "Chemical Engineering",
        "institution": "HUST",
        "years": "2018",
        "linkedinProfile": "",
        "email": ""
      },
      {
        "name": "Jared Wheeler",
        "department": "Computer Science",
        "institution": "TAMU",
        "years": "2018",
        "linkedinProfile": "",
        "email": ""
      },
      {
        "name": "Tyler Sizemore",
        "department": "Mechanical Engineering",
        "institution": "TAMU",
        "years": "2018-2019",
        "linkedinProfile": "",
        "email": ""
      },
      {
        "name": "Matthew Foley",
        "department": "Civil Engineering",
        "institution": "TAMU",
        "years": "2018-2019",
        "linkedinProfile": "",
        "email": ""
        },
        {
          "name": "Christopher Lira",
          "department": "Civil Engineering",
          "institution": "TAMU",
          "years": "2017-2018",
          "linkedinProfile": "",
          "email": ""
        },
        {
          "name": "Ly-Na Tran",
          "department": "Biomedical Science",
          "institution": "TAMU",
          "years": "2017-2019",
          "linkedinProfile": "",
          "email": ""
        },
        {
          "name": "Jacob Bruce",
          "department": "Civil Engineering",
          "institution": "TAMU",
          "years": "2019-",
          "linkedinProfile": "",
          "email": ""
        },
        {
          "name": "Elizabeth Clark",
          "department": "Civil Engineering",
          "institution": "Virginia Tech",
          "years": "2017",
          "linkedinProfile": "",
          "email": ""
        },
        {
          "name": "Anthony Teo",
          "department": "CS and Engineering",
          "institution": "TAMU",
          "years": "2018-2019",
          "linkedinProfile": "",
          "email": ""
        },
        {
          "name": "Urel Djiogan",
          "department": "CS and Engineering",
          "institution": "TAMU",
          "years": "2019",
          "linkedinProfile": "",
          "email": ""
        },
        {
          "name": "Richard Padilla",
          "department": "CS and Engineering",
          "institution": "TAMU",
          "years": "2018-2019",
          "linkedinProfile": "",
          "email": ""
        },
        {
          "name": "Daxton Davidson",
          "department": "Civil Engineering",
          "institution": "TAMU",
          "years": "2018",
          "linkedinProfile": "",
          "email": ""
        },
        {
          "name": "Michelle Zupancich",
          "department": "Civil Engineering",
          "institution": "TAMU",
          "years": "2016",
          "linkedinProfile": "",
          "email": ""
        }
      ]
    }
